recbole/__init__.py
recbole/config/__init__.py
recbole/config/configurator.py
recbole/data/__init__.py
recbole/data/interaction.py
recbole/data/transform.py
recbole/data/utils.py
recbole/data/dataloader/__init__.py
recbole/data/dataloader/abstract_dataloader.py
recbole/data/dataloader/general_dataloader.py
recbole/data/dataloader/knowledge_dataloader.py
recbole/data/dataloader/user_dataloader.py
recbole/data/dataset/__init__.py
recbole/data/dataset/customized_dataset.py
recbole/data/dataset/dataset.py
recbole/data/dataset/decisiontree_dataset.py
recbole/data/dataset/kg_dataset.py
recbole/data/dataset/kg_seq_dataset.py
recbole/data/dataset/sequential_dataset.py
recbole/dataset_example/ml-100k/ml-100k.inter
recbole/dataset_example/ml-100k/ml-100k.item
recbole/dataset_example/ml-100k/ml-100k.kg
recbole/dataset_example/ml-100k/ml-100k.link
recbole/dataset_example/ml-100k/ml-100k.user
recbole/evaluator/__init__.py
recbole/evaluator/base_metric.py
recbole/evaluator/collector.py
recbole/evaluator/evaluator.py
recbole/evaluator/metrics.py
recbole/evaluator/register.py
recbole/evaluator/utils.py
recbole/model/__init__.py
recbole/model/abstract_recommender.py
recbole/model/init.py
recbole/model/layers.py
recbole/model/loss.py
recbole/model/context_aware_recommender/__init__.py
recbole/model/context_aware_recommender/afm.py
recbole/model/context_aware_recommender/autoint.py
recbole/model/context_aware_recommender/dcn.py
recbole/model/context_aware_recommender/dcnv2.py
recbole/model/context_aware_recommender/deepfm.py
recbole/model/context_aware_recommender/dssm.py
recbole/model/context_aware_recommender/eulernet.py
recbole/model/context_aware_recommender/ffm.py
recbole/model/context_aware_recommender/fignn.py
recbole/model/context_aware_recommender/fm.py
recbole/model/context_aware_recommender/fnn.py
recbole/model/context_aware_recommender/fwfm.py
recbole/model/context_aware_recommender/kd_dagfm.py
recbole/model/context_aware_recommender/lr.py
recbole-1.2.1.dist-info/LICENSE
recbole-1.2.1.dist-info/METADATA
recbole-1.2.1.dist-info/WHEEL
recbole-1.2.1.dist-info/top_level.txt
recbole-1.2.1.dist-info/RECORD
